LICENSE
MANIFEST.in
README.md
setup.cfg
setup.py
bce_sam_translator.egg-info/PKG-INFO
bce_sam_translator.egg-info/SOURCES.txt
bce_sam_translator.egg-info/dependency_links.txt
bce_sam_translator.egg-info/requires.txt
bce_sam_translator.egg-info/top_level.txt
requirements/base.txt
requirements/dev.txt
samtranslator/__init__.py
samtranslator/region_configuration.py
samtranslator/yaml_helper.py
samtranslator/intrinsics/__init__.py
samtranslator/intrinsics/actions.py
samtranslator/intrinsics/resolver.py
samtranslator/intrinsics/resource_refs.py
samtranslator/model/__init__.py
samtranslator/model/apigateway.py
samtranslator/model/codedeploy.py
samtranslator/model/dynamodb.py
samtranslator/model/events.py
samtranslator/model/exceptions.py
samtranslator/model/function_policies.py
samtranslator/model/iam.py
samtranslator/model/intrinsics.py
samtranslator/model/iot.py
samtranslator/model/lambda_.py
samtranslator/model/log.py
samtranslator/model/naming.py
samtranslator/model/s3.py
samtranslator/model/sam_resources.py
samtranslator/model/sns.py
samtranslator/model/types.py
samtranslator/model/update_policy.py
samtranslator/model/api/__init__.py
samtranslator/model/api/api_generator.py
samtranslator/model/eventsources/__init__.py
samtranslator/model/eventsources/cloudwatchlogs.py
samtranslator/model/eventsources/pull.py
samtranslator/model/eventsources/push.py
samtranslator/model/preferences/__init__.py
samtranslator/model/preferences/deployment_preference.py
samtranslator/model/preferences/deployment_preference_collection.py
samtranslator/model/s3_utils/__init__.py
samtranslator/model/s3_utils/uri_parser.py
samtranslator/model/tags/__init__.py
samtranslator/model/tags/resource_tagging.py
samtranslator/parser/__init__.py
samtranslator/parser/parser.py
samtranslator/plugins/__init__.py
samtranslator/plugins/api/__init__.py
samtranslator/plugins/api/implicit_api_plugin.py
samtranslator/plugins/globals/__init__.py
samtranslator/plugins/globals/globals.py
samtranslator/plugins/globals/globals_plugin.py
samtranslator/plugins/policies/__init__.py
samtranslator/plugins/policies/policy_templates_plugin.py
samtranslator/policy_template_processor/__init__.py
