Metadata-Version: 2.1
Name: bce-sam-translator
Version: 0.0.1
Summary: BCE SAM Translator
Home-page: https://github.com/bcelabs/serverless-application-model
License: Apache License 2.0
Keywords: BCE SAM Serverless Application Model
Platform: UNKNOWN
Classifier: Development Status :: 4 - Beta
Classifier: Environment :: Console
Classifier: Environment :: Other Environment
Classifier: Intended Audience :: Developers
Classifier: Intended Audience :: Information Technology
Classifier: License :: OSI Approved :: Apache Software License
Classifier: Operating System :: OS Independent
Classifier: Programming Language :: Python
Classifier: Programming Language :: Python :: 2.7
Classifier: Topic :: Internet
Classifier: Topic :: Software Development :: Build Tools
Classifier: Topic :: Utilities
Provides-Extra: dev
